patternmatching/__init__.py
patternmatching-3.0.1.dist-info/LICENSE
patternmatching-3.0.1.dist-info/METADATA
patternmatching-3.0.1.dist-info/WHEEL
patternmatching-3.0.1.dist-info/top_level.txt
patternmatching-3.0.1.dist-info/RECORD
